zetane/XAI_dashboard.cp39-win_amd64.pyd
zetane/XAI_dashboard.py
zetane/ZetaneViz.cp39-win_amd64.pyd
zetane/ZetaneViz.py
zetane/__init__.py
zetane/__main__.py
zetane/context.cp39-win_amd64.pyd
zetane/context.py
zetane/dashboard.cp39-win_amd64.pyd
zetane/dashboard.py
zetane/expose_node_outputs.cp39-win_amd64.pyd
zetane/inference_dashboard.cp39-win_amd64.pyd
zetane/inference_dashboard.py
zetane/load.cp39-win_amd64.pyd
zetane/load.py
zetane/numpy_utils.cp39-win_amd64.pyd
zetane/numpy_utils.py
zetane/save.cp39-win_amd64.pyd
zetane/save.py
zetane/snapshot.cp39-win_amd64.pyd
zetane/snapshot.py
zetane/socket.cp39-win_amd64.pyd
zetane/socket.py
zetane/utils.cp39-win_amd64.pyd
zetane/utils.py
zetane/version.py
zetane/analytics/__init__.py
zetane/analytics/async_buffered_consumer.cp39-win_amd64.pyd
zetane/analytics/mixpanel.cp39-win_amd64.pyd
zetane/analytics/mixpanel_async.cp39-win_amd64.pyd
zetane/analytics/zanalytics.cp39-win_amd64.pyd
zetane/explain/ModelTSNE.cp39-win_amd64.pyd
zetane/explain/ModelTSNE.py
zetane/explain/PCA.cp39-win_amd64.pyd
zetane/explain/PCA.py
zetane/explain/__init__.py
zetane/explain/tsne.cp39-win_amd64.pyd
zetane/explain/tsne.py
zetane/explain/algorithms/__init__.py
zetane/explain/algorithms/inverted_representation.cp39-win_amd64.pyd
zetane/explain/algorithms/inverted_representation.py
zetane/explain/keras/__init__.py
zetane/explain/keras/explainability_methods.cp39-win_amd64.pyd
zetane/explain/keras/explainability_methods.py
zetane/explain/keras/keras_utils.cp39-win_amd64.pyd
zetane/explain/keras/keras_utils.py
zetane/explain/keras/zetane_pruning.cp39-win_amd64.pyd
zetane/explain/keras/zetane_pruning.py
zetane/explain/keras/algorithms/__init__.py
zetane/explain/keras/algorithms/keras_gradcam.cp39-win_amd64.pyd
zetane/explain/keras/algorithms/keras_gradcam.py
zetane/explain/keras/algorithms/keras_integrated_gradients.cp39-win_amd64.pyd
zetane/explain/keras/algorithms/keras_integrated_gradients.py
zetane_engine-1.7.4.dist-info/LICENSE.md
zetane_engine-1.7.4.dist-info/METADATA
zetane_engine-1.7.4.dist-info/WHEEL
zetane_engine-1.7.4.dist-info/top_level.txt
zetane_engine-1.7.4.dist-info/RECORD
