Metadata-Version: 2.1
Name: zetane-engine
Version: 1.7.4
Summary: The Zetane Engine
Home-page: https://zetane.com/download
Author: Zetane Systems
Author-email: info@zetane.com
Keywords: AI,Machine Learning,Explainability,Visualization
Classifier: Programming Language :: Python :: 3
Classifier: License :: Other/Proprietary License
Classifier: Operating System :: OS Independent
Requires-Python: >=3.8
License-File: LICENSE.md
Requires-Dist: pynng
Requires-Dist: matplotlib
Requires-Dist: opencv-python
Requires-Dist: cmake
Requires-Dist: tqdm
Requires-Dist: Pillow
Requires-Dist: scikit-learn
Requires-Dist: lime
Requires-Dist: onnxconverter-common
Requires-Dist: protobuf (<3.20,>=3.12)
Requires-Dist: tf2onnx
Requires-Dist: onnx
